fed3live/__init__.py
fed3live/fed3live.py
fed3live-0.0.2.dist-info/METADATA
fed3live-0.0.2.dist-info/WHEEL
fed3live-0.0.2.dist-info/top_level.txt
fed3live-0.0.2.dist-info/RECORD
